tsqlxlsx/__init__.py
tsqlxlsx/__main__.py
tsqlxlsx/data_loader.py
tsqlxlsx/sql_ddl.py
tsqlxlsx/tsql_connector.py
tsqlxlsx-1.0.2.dist-info/METADATA
tsqlxlsx-1.0.2.dist-info/WHEEL
tsqlxlsx-1.0.2.dist-info/top_level.txt
tsqlxlsx-1.0.2.dist-info/RECORD
