Metadata-Version: 2.1
Name: tsqlxlsx
Version: 1.0.2
Summary: Pip package for pushing files csv, xlsx to sql server
Home-page: UNKNOWN
Author: bgovi (Brandon Govindarajoo)
Author-email: <bgovi@umich.edu>
License: UNKNOWN
Keywords: python,tsql,xlsx
Platform: UNKNOWN
Classifier: Development Status :: 1 - Planning
Classifier: Intended Audience :: Developers
Classifier: Programming Language :: Python :: 3
Classifier: Operating System :: Unix
Classifier: Operating System :: MacOS :: MacOS X
Classifier: Operating System :: Microsoft :: Windows
Requires-Dist: pandas
Requires-Dist: pyodbc
